azure/mgmt/powerbiembedded/__init__.py
azure/mgmt/powerbiembedded/_configuration.py
azure/mgmt/powerbiembedded/_patch.py
azure/mgmt/powerbiembedded/_power_bi_embedded_management_client.py
azure/mgmt/powerbiembedded/_serialization.py
azure/mgmt/powerbiembedded/_vendor.py
azure/mgmt/powerbiembedded/_version.py
azure/mgmt/powerbiembedded/py.typed
azure/mgmt/powerbiembedded/aio/__init__.py
azure/mgmt/powerbiembedded/aio/_configuration.py
azure/mgmt/powerbiembedded/aio/_patch.py
azure/mgmt/powerbiembedded/aio/_power_bi_embedded_management_client.py
azure/mgmt/powerbiembedded/aio/_vendor.py
azure/mgmt/powerbiembedded/aio/operations/__init__.py
azure/mgmt/powerbiembedded/aio/operations/_patch.py
azure/mgmt/powerbiembedded/aio/operations/_power_bi_embedded_management_client_operations.py
azure/mgmt/powerbiembedded/aio/operations/_workspace_collections_operations.py
azure/mgmt/powerbiembedded/aio/operations/_workspaces_operations.py
azure/mgmt/powerbiembedded/models/__init__.py
azure/mgmt/powerbiembedded/models/_models_py3.py
azure/mgmt/powerbiembedded/models/_patch.py
azure/mgmt/powerbiembedded/models/_power_bi_embedded_management_client_enums.py
azure/mgmt/powerbiembedded/operations/__init__.py
azure/mgmt/powerbiembedded/operations/_patch.py
azure/mgmt/powerbiembedded/operations/_power_bi_embedded_management_client_operations.py
azure/mgmt/powerbiembedded/operations/_workspace_collections_operations.py
azure/mgmt/powerbiembedded/operations/_workspaces_operations.py
azure_mgmt_powerbiembedded-3.0.0.dist-info/LICENSE
azure_mgmt_powerbiembedded-3.0.0.dist-info/METADATA
azure_mgmt_powerbiembedded-3.0.0.dist-info/WHEEL
azure_mgmt_powerbiembedded-3.0.0.dist-info/top_level.txt
azure_mgmt_powerbiembedded-3.0.0.dist-info/RECORD
